glean_client_api/__init__.py
glean_client_api/api_client.py
glean_client_api/api_response.py
glean_client_api/configuration.py
glean_client_api/exceptions.py
glean_client_api/py.typed
glean_client_api/rest.py
glean_client_api/api/__init__.py
glean_client_api/api/activity_api.py
glean_client_api/api/announcements_api.py
glean_client_api/api/answers_api.py
glean_client_api/api/authentication_api.py
glean_client_api/api/calendar_api.py
glean_client_api/api/chat_api.py
glean_client_api/api/collections_api.py
glean_client_api/api/displayable_lists_api.py
glean_client_api/api/documents_api.py
glean_client_api/api/entities_api.py
glean_client_api/api/images_api.py
glean_client_api/api/insights_api.py
glean_client_api/api/messages_api.py
glean_client_api/api/pins_api.py
glean_client_api/api/search_api.py
glean_client_api/api/shortcuts_api.py
glean_client_api/api/summarize_api.py
glean_client_api/api/tools_api.py
glean_client_api/api/user_api.py
glean_client_api/api/verification_api.py
glean_client_api/models/__init__.py
glean_client_api/models/activity.py
glean_client_api/models/activity_event.py
glean_client_api/models/activity_event_params.py
glean_client_api/models/add_collection_items_error.py
glean_client_api/models/add_collection_items_request.py
glean_client_api/models/add_collection_items_response.py
glean_client_api/models/add_credential_request.py
glean_client_api/models/added_collections.py
glean_client_api/models/agent_client_config.py
glean_client_api/models/agent_config.py
glean_client_api/models/ai_app_action_counts.py
glean_client_api/models/ai_apps_insights_response.py
glean_client_api/models/ai_insights_response.py
glean_client_api/models/alert_data.py
glean_client_api/models/announcement.py
glean_client_api/models/announcement_all_of_viewer_info.py
glean_client_api/models/announcement_channel.py
glean_client_api/models/announcement_error.py
glean_client_api/models/announcement_mutable_properties.py
glean_client_api/models/anonymous_event.py
glean_client_api-1.0.0.dist-info/METADATA
glean_client_api-1.0.0.dist-info/WHEEL
glean_client_api-1.0.0.dist-info/top_level.txt
glean_client_api-1.0.0.dist-info/RECORD
