Metadata-Version: 2.1
Name: glean-client-api
Version: 1.0.0
Summary: Glean Client API
Home-page: 
Author: OpenAPI Generator community
Author-email: support@glean.com
Keywords: OpenAPI,OpenAPI-Generator,Glean Client API
Requires-Dist: urllib3 <2.1.0,>=1.25.3
Requires-Dist: python-dateutil
Requires-Dist: pydantic >=2
Requires-Dist: typing-extensions >=4.7.1
